[
    {
        "key": "dbln",
        "value": "%7B%22100001721265051%22%3A%22poMZnQIw%22%2C%22100001950310288%22%3A%220bJKCTSi%22%7D",
        "domain": "facebook.com",
        "path": "/login/device-based/",
        "hostOnly": false,
        "creation": "2025-01-30T20:32:55.361Z",
        "lastAccessed": "2025-01-30T20:32:55.362Z"
    },
    {
        "key": "datr",
        "value": "SgGZZyXyPXEEr_BbwiBFEsn8",
        "domain": "facebook.com",
        "path": "/",
        "hostOnly": false,
        "creation": "2025-01-30T20:32:55.362Z",
        "lastAccessed": "2025-01-30T20:32:55.362Z"
    },
    {
        "key": "sb",
        "value": "SgGZZ16iSjifMZtYMQeFcgqx",
        "domain": "facebook.com",
        "path": "/",
        "hostOnly": false,
        "creation": "2025-01-30T20:32:55.362Z",
        "lastAccessed": "2025-01-30T20:32:55.362Z"
    },
    {
        "key": "vpd",
        "value": "v1%3B742x384x1.875",
        "domain": "facebook.com",
        "path": "/",
        "hostOnly": false,
        "creation": "2025-01-30T20:32:55.362Z",
        "lastAccessed": "2025-01-30T20:32:55.362Z"
    },
    {
        "key": "locale",
        "value": "es_LA",
        "domain": "facebook.com",
        "path": "/",
        "hostOnly": false,
        "creation": "2025-01-30T20:32:55.362Z",
        "lastAccessed": "2025-01-30T20:32:55.362Z"
    },
    {
        "key": "m_pixel_ratio",
        "value": "1.875",
        "domain": "facebook.com",
        "path": "/",
        "hostOnly": false,
        "creation": "2025-01-30T20:32:55.362Z",
        "lastAccessed": "2025-01-30T20:32:55.362Z"
    },
    {
        "key": "wd",
        "value": "384x742",
        "domain": "facebook.com",
        "path": "/",
        "hostOnly": false,
        "creation": "2025-01-30T20:32:55.362Z",
        "lastAccessed": "2025-01-30T20:32:55.362Z"
    },
    {
        "key": "c_user",
        "value": "100001950310288",
        "domain": "facebook.com",
        "path": "/",
        "hostOnly": false,
        "creation": "2025-01-30T20:32:55.362Z",
        "lastAccessed": "2025-01-30T20:32:55.362Z"
    },
    {
        "key": "xs",
        "value": "41%3AkskdNjz7uJqiww%3A2%3A1738269166%3A-1%3A-1",
        "domain": "facebook.com",
        "path": "/",
        "hostOnly": false,
        "creation": "2025-01-30T20:32:55.362Z",
        "lastAccessed": "2025-01-30T20:32:55.362Z"
    },
    {
        "key": "fbl_st",
        "value": "101334567%3BT%3A28971152",
        "domain": "facebook.com",
        "path": "/",
        "hostOnly": false,
        "creation": "2025-01-30T20:32:55.362Z",
        "lastAccessed": "2025-01-30T20:32:55.362Z"
    },
    {
        "key": "wl_cbv",
        "value": "v2%3Bclient_version%3A2729%3Btimestamp%3A1738269168",
        "domain": "facebook.com",
        "path": "/",
        "hostOnly": false,
        "creation": "2025-01-30T20:32:55.362Z",
        "lastAccessed": "2025-01-30T20:32:55.362Z"
    }
]
